simplaza/__init__.py
simplaza/__main__.py
simplaza/api.py
simplaza-0.1.6.dist-info/entry_points.txt
simplaza-0.1.6.dist-info/LICENSE
simplaza-0.1.6.dist-info/METADATA
simplaza-0.1.6.dist-info/WHEEL
simplaza-0.1.6.dist-info/RECORD
