Metadata-Version: 2.1
Name: simplaza
Version: 0.1.6
Summary: SimPlaza unoffical CLI - Query and download torrent files from SimPlaza directly from your terminal
License: GPL-3.0
Author: Jacob
Author-email: jayy2004@gmx.co.uk
Requires-Python: >=3.10,<4.0
Classifier: License :: OSI Approved :: GNU General Public License v3 (GPLv3)
Classifier: Programming Language :: Python :: 3
Classifier: Programming Language :: Python :: 3.10
Classifier: Programming Language :: Python :: 3.11
Classifier: Programming Language :: Python :: 3.12
Requires-Dist: beautifulsoup4 (>=4.11.1,<5.0.0)
Requires-Dist: click (>=8.1.3,<9.0.0)
Requires-Dist: magneturi (>=1.3,<2.0)
Requires-Dist: requests (>=2.28.1,<3.0.0)
Requires-Dist: rich (>=12.5.1,<13.0.0)
